sonic_channel_scraper/__init__.py
sonic_channel_scraper-1.1.0.dist-info/entry_points.txt
sonic_channel_scraper-1.1.0.dist-info/LICENSE
sonic_channel_scraper-1.1.0.dist-info/METADATA
sonic_channel_scraper-1.1.0.dist-info/WHEEL
sonic_channel_scraper-1.1.0.dist-info/RECORD
